MANIFEST.in
README.md
setup.cfg
setup.py
flask_csp/__init__.py
flask_csp/__init__.pyc
flask_csp/csp.py
flask_csp/csp_default.json
flask_csp/test_csp.py
flask_csp.egg-info/PKG-INFO
flask_csp.egg-info/SOURCES.txt
flask_csp.egg-info/dependency_links.txt
flask_csp.egg-info/top_level.txt