Metadata-Version: 1.1
Name: flask-csp
Version: 0.10
Summary: Flask Content Security Policy header support
Home-page: https://github.com/twaldear/flask-csp
Author: Tristan Waldear
Author-email: trwaldear@gmail.com
License: MIT
Download-URL: https://github.com/twaldear/flask-csp/tarball/0.10
Keywords: flask,csp,header
Platform: UNKNOWN
Classifier: Development Status :: 4 - Beta
Classifier: Framework :: Flask
Classifier: License :: OSI Approved :: MIT License
Classifier: Operating System :: OS Independent
Classifier: Programming Language :: Python
Classifier: Topic :: Software Development :: Libraries :: Python Modules
